README.md
setup.cfg
setup.py
tictactoeadarbha/__init__.py
tictactoeadarbha/game.py
tictactoeadarbha/player.py
tictactoeadarbha.egg-info/PKG-INFO
tictactoeadarbha.egg-info/SOURCES.txt
tictactoeadarbha.egg-info/dependency_links.txt
tictactoeadarbha.egg-info/not-zip-safe
tictactoeadarbha.egg-info/top_level.txt