Metadata-Version: 1.0
Name: tictactoeadarbha
Version: 0.1
Summary: Pieces for creating a TicTacToe Game
Home-page: UNKNOWN
Author: UNKNOWN
Author-email: UNKNOWN
License: UNKNOWN
Platform: UNKNOWN
